local_connect/__init__.py
local_connect/cli.py
local_connect/paragraph_clip_client.py
local_connect/paragraph_clip_server.py
local_connect/single_char_client.py
local_connect/single_char_server.py
local_connect/utils.py
local_connect-0.0.3.dist-info/licenses/LICENSE
local_connect-0.0.3.dist-info/METADATA
local_connect-0.0.3.dist-info/WHEEL
local_connect-0.0.3.dist-info/entry_points.txt
local_connect-0.0.3.dist-info/top_level.txt
local_connect-0.0.3.dist-info/RECORD
