Metadata-Version: 2.4
Name: local-connect
Version: 0.0.3
Summary: library that contains scripts to connect between laptops in local network
Author-email: truongbaan <truongbaansoftware@gmail.com>
License-Expression: MIT
Project-URL: Homepage, https://github.com/truongbaan/Local-Connect-Python
Requires-Python: >=3.9.13
License-File: LICENSE
Requires-Dist: mss
Requires-Dist: opencv-python
Requires-Dist: numpy
Requires-Dist: keyboard
Requires-Dist: pyperclip
Dynamic: license-file
